[
  {
    "timestamp": "13:38:59",
    "speaker": "user",
    "message": "Hi"
  },
  {
    "timestamp": "13:39:14",
    "speaker": "user",
    "message": "Can i have link to book the facility."
  },
  {
    "timestamp": "13:40:55",
    "speaker": "user",
    "message": "thanks"
  },
  {
    "timestamp": "13:41:02",
    "speaker": "user",
    "message": "Thats all for now"
  },
  {
    "timestamp": "13:39:05",
    "speaker": "helpdesk",
    "message": "Hi PERSON_FIRSTNAME_3, how can we assist u?"
  },
  {
    "timestamp": "13:40:03",
    "speaker": "helpdesk",
    "message": "Go to this link --> <a href=\"https://libfaq.smu.edu.sg/faq/134718\" target=\"_blank\">https://libfaq.smu.edu.sg/faq/134718</a>"
  },
  {
    "timestamp": "13:40:54",
    "speaker": "helpdesk",
    "message": "Would there be other queries that I can help with?"
  },
  {
    "timestamp": "13:40:58",
    "speaker": "helpdesk",
    "message": "Sure"
  }
]