[
  {"timestamp": "12:56:29", "speaker": "User", "message": "Hi PERSON_FIRSTNAME_2"},
  {"timestamp": "12:56:34", "speaker": "User", "message": "how can we help you today"},
  {"timestamp": "12:57:09", "speaker": "casie", "message": "hi, can i ask if smu students can access free straits time subscription?"},
  {"timestamp": "12:57:50", "speaker": "casie", "message": "and how to find it"},
  {"timestamp": "12:58:43", "speaker": "casie", "message": "i see, what about normal subscriptions? like on the app or website"},
  {"timestamp": "12:59:09", "speaker": "casie", "message": "yup"},
  {"timestamp": "13:00:03", "speaker": "casie", "message": "ohh i see so i have to access through the sch website?"},
  {"timestamp": "13:00:49", "speaker": "casie", "message": "okay, understand! thanks PERSON_FIRSTNAME_1!"},
  {"timestamp": "13:00:55", "speaker": "casie", "message": ":)"},
  {"timestamp": "13:01:11", "speaker": "casie", "message": "that will be all thanks"},
  {"timestamp": "13:01:24", "speaker": "casie", "message": "yes please"},
  {"timestamp": "13:01:28", "speaker": "casie", "message": "thanks sm!"},

  {"timestamp": "12:56:41", "speaker": "Help Desk", "message": "yup"},
  {"timestamp": "12:57:26", "speaker": "Help Desk", "message": "you can access the newspapers we have here:<a href=\"https://researchguides.smu.edu.sg/az.php?t=37369&amp;p=1\" target=\"_blank\">https://researchguides.smu.edu.sg/az.php?t=37369&amp;p=1</a>"},
  {"timestamp": "12:57:50", "speaker": "Help Desk", "message": "there is a maximum number of users who can access the straits times at any given time"},
  {"timestamp": "12:58:20", "speaker": "Help Desk", "message": "so if you can't access it, do try at a non-peak period"},
  {"timestamp": "12:58:23", "speaker": "Help Desk", "message": "eg avoid the morning"},
  {"timestamp": "12:59:24", "speaker": "Help Desk", "message": "you can click on the Straits Times link in the link I just sent you"},
  {"timestamp": "12:59:30", "speaker": "Help Desk", "message": "and that will bring you to the website"},
  {"timestamp": "12:59:45", "speaker": "Help Desk", "message": "our subscription doesn't give you access via the app"},
  {"timestamp": "13:00:30", "speaker": "Help Desk", "message": "yep coz they need to verify the access as through the institution"},
  {"timestamp": "13:00:46", "speaker": "Help Desk", "message": "you don't get individual login details"},
  {"timestamp": "13:00:58", "speaker": "Help Desk", "message": "no worries!"},
  {"timestamp": "13:01:03", "speaker": "Help Desk", "message": "anything else you need help with?"},
  {"timestamp": "13:01:15", "speaker": "Help Desk", "message": "ok sure"},
  {"timestamp": "13:01:18", "speaker": "Help Desk", "message": "I will end the chat then"},
  {"timestamp": "13:01:24", "speaker": "Help Desk", "message": "all the best for your exams!"}
]